MANIFEST.in
README.md
requirements.txt
setup.cfg
setup.py
versioneer.py
botcity/plugins/ms365/credentials/__init__.py
botcity/plugins/ms365/credentials/_version.py
botcity/plugins/ms365/credentials/plugin.py
botcity_ms365_credentials_plugin.egg-info/PKG-INFO
botcity_ms365_credentials_plugin.egg-info/SOURCES.txt
botcity_ms365_credentials_plugin.egg-info/dependency_links.txt
botcity_ms365_credentials_plugin.egg-info/requires.txt
botcity_ms365_credentials_plugin.egg-info/top_level.txt
tests/test_import.py
tests/test_plugin.py