Metadata-Version: 2.1
Name: botcity-ms365-credentials-plugin
Version: 0.1.0
Home-page: https://github.com/botcity-dev/bot-ms365-credentials-plugin-python.git
Requires-Python: >=3.7
